hunter_mcp/__init__.py
hunter_mcp/client.py
mseep_hunter_mcp-0.1.2.dist-info/licenses/LICENSE.md
mseep_hunter_mcp-0.1.2.dist-info/METADATA
mseep_hunter_mcp-0.1.2.dist-info/WHEEL
mseep_hunter_mcp-0.1.2.dist-info/top_level.txt
mseep_hunter_mcp-0.1.2.dist-info/RECORD
