Metadata-Version: 2.4
Name: mseep-hunter-mcp
Version: 0.1.2
Summary: An MCP interface for the Hunter API
Author-email: mseep <support@skydeck.ai>
Requires-Python: >=3.13
License-File: LICENSE.md
Requires-Dist: httpx>=0.28.1
Requires-Dist: mcp[cli]>=1.8.1
Dynamic: license-file
